LICENSE
MANIFEST.in
README.rst
setup.py
ansible_prngmgr_inventory.egg-info/PKG-INFO
ansible_prngmgr_inventory.egg-info/SOURCES.txt
ansible_prngmgr_inventory.egg-info/dependency_links.txt
ansible_prngmgr_inventory.egg-info/entry_points.txt
ansible_prngmgr_inventory.egg-info/requires.txt
ansible_prngmgr_inventory.egg-info/top_level.txt
packaging/VERSION
packaging/requirements-test.txt
packaging/requirements.txt
prngmgr_inventory/__init__.py
prngmgr_inventory/command_line.py
prngmgr_inventory/configuration.py
prngmgr_inventory/inventory.py
prngmgr_inventory/parser.py
prngmgr_inventory/prngmgr_inventory.ini.example
prngmgr_inventory/tests/__init__.py
prngmgr_inventory/tests/prngmgr_inventory_test.ini
prngmgr_inventory/tests/test_cases.py
prngmgr_inventory/tests/test_host_data.json
prngmgr_inventory/tests/test_list_data.json